sap_config_guard/__init__.py
sap_config_guard/cli/__init__.py
sap_config_guard/cli/main.py
sap_config_guard/core/__init__.py
sap_config_guard/core/loader.py
sap_config_guard/core/schema.py
sap_config_guard/core/validator.py
sap_config_guard/diff/__init__.py
sap_config_guard/diff/env_diff.py
sap_config_guard/rules/__init__.py
sap_config_guard/rules/sap_rules.yaml
sap_config_guard-0.1.0.dist-info/licenses/LICENSE
tests/__init__.py
tests/test_diff.py
tests/test_loader.py
tests/test_validator.py
sap_config_guard-0.1.0.dist-info/METADATA
sap_config_guard-0.1.0.dist-info/WHEEL
sap_config_guard-0.1.0.dist-info/entry_points.txt
sap_config_guard-0.1.0.dist-info/top_level.txt
sap_config_guard-0.1.0.dist-info/RECORD
